psme/__init__.py
psme/engine.py
psme/subcommand.py
psme/tests/__init__.py
psme/tests/test_engine.py
psme-0.1.0.dist-info/LICENSE
psme-0.1.0.dist-info/WHEEL
psme-0.1.0.dist-info/METADATA
psme-0.1.0.dist-info/RECORD
