Metadata-Version: 2.1
Name: psme
Version: 0.1.0
Summary: Python subcommands made easy.
License: MIT
Author: Clay McLeod
Author-email: clay.l.mcleod@gmail.com
Requires-Python: >=3.9,<4.0
Classifier: License :: OSI Approved :: MIT License
Classifier: Programming Language :: Python :: 3
Classifier: Programming Language :: Python :: 3.10
Classifier: Programming Language :: Python :: 3.9
